LICENSE
pygitstat/__init__.py
pygitstat/gitstat.py
pygitstat-0.5.1.dist-info/entry_points.txt
pygitstat-0.5.1.dist-info/LICENSE
pygitstat-0.5.1.dist-info/WHEEL
pygitstat-0.5.1.dist-info/METADATA
pygitstat-0.5.1.dist-info/RECORD
