Metadata-Version: 2.1
Name: pygitstat
Version: 0.5.1
Summary: Succinctly display information about git repositories.
Home-page: https://gitlab.com/johnivore/gitstat
License: GPL-3.0-or-later
Keywords: git
Author: John Begenisich
Author-email: john.begenisich@outlook.com
Requires-Python: >=3.6.1,<4.0.0
Classifier: Development Status :: 4 - Beta
Classifier: Environment :: Console
Classifier: Intended Audience :: Developers
Classifier: Intended Audience :: System Administrators
Classifier: License :: OSI Approved :: GNU General Public License v3 or later (GPLv3+)
Classifier: Operating System :: OS Independent
Classifier: Programming Language :: Python
Classifier: Programming Language :: Python :: 3
Classifier: Programming Language :: Python :: 3 :: Only
Classifier: Programming Language :: Python :: 3.10
Classifier: Programming Language :: Python :: 3.6
Classifier: Programming Language :: Python :: 3.7
Classifier: Programming Language :: Python :: 3.8
Classifier: Programming Language :: Python :: 3.9
Classifier: Topic :: Software Development :: Version Control :: Git
Requires-Dist: Colr (>=0.9.1,<0.10.0)
Requires-Dist: click (>=7.1.2,<8.0.0)
Requires-Dist: click-default-group (>=1.2.2,<2.0.0)
Requires-Dist: tqdm (>=4.54.1,<5.0.0)
Requires-Dist: typer (>=0.3.2,<0.4.0)
Project-URL: Repository, https://gitlab.com/johnivore/gitstat
